{
	"type": "minecraft:block",
	"pools": [
		{
			"rolls": 1,
			"entries": [
				{
					"type": "minecraft:item",
					"name": "beautify:warped_trellis",
					"conditions": [
						{
							"condition": "minecraft:block_state_property",
							"block": "beautify:warped_trellis",
							"properties": {
								"flowers": "0"
							}
						}
					]
				},
				{
					"type": "minecraft:loot_table",
					"name": "beautify:blocks/warped_rose_trellis",
					"conditions": [
						{
							"condition": "minecraft:block_state_property",
							"block": "beautify:warped_trellis",
							"properties": {
								"flowers": "1"
							}
						}
					]
				},
				{
					"type": "minecraft:loot_table",
					"name": "beautify:blocks/warped_sunflower_trellis",
					"conditions": [
						{
							"condition": "minecraft:block_state_property",
							"block": "beautify:warped_trellis",
							"properties": {
								"flowers": "2"
							}
						}
					]
				},
				{
					"type": "minecraft:loot_table",
					"name": "beautify:blocks/warped_peony_trellis",
					"conditions": [
						{
							"condition": "minecraft:block_state_property",
							"block": "beautify:warped_trellis",
							"properties": {
								"flowers": "3"
							}
						}
					]
				},
				{
					"type": "minecraft:loot_table",
					"name": "beautify:blocks/warped_lilac_trellis",
					"conditions": [
						{
							"condition": "minecraft:block_state_property",
							"block": "beautify:warped_trellis",
							"properties": {
								"flowers": "4"
							}
						}
					]
				},
				{
					"type": "minecraft:loot_table",
					"name": "beautify:blocks/warped_vine_trellis",
					"conditions": [
						{
							"condition": "minecraft:block_state_property",
							"block": "beautify:warped_trellis",
							"properties": {
								"flowers": "5"
							}
						}
					]
				},
				{
					"type": "minecraft:loot_table",
					"name": "beautify:blocks/warped_weeping_vines_trellis",
					"conditions": [
						{
							"condition": "minecraft:block_state_property",
							"block": "beautify:warped_trellis",
							"properties": {
								"flowers": "6"
							}
						}
					]
				},
				{
					"type": "minecraft:loot_table",
					"name": "beautify:blocks/warped_twisting_vines_trellis",
					"conditions": [
						{
							"condition": "minecraft:block_state_property",
							"block": "beautify:warped_trellis",
							"properties": {
								"flowers": "7"
							}
						}
					]
				},
				{
					"type": "minecraft:loot_table",
					"name": "beautify:blocks/warped_lichen_trellis",
					"conditions": [
						{
							"condition": "minecraft:block_state_property",
							"block": "beautify:warped_trellis",
							"properties": {
								"flowers": "8"
							}
						}
					]
				}
			]
		}
	]
}
